odoo/addons/shopinvader_product_seo/README.rst
odoo/addons/shopinvader_product_seo/__init__.py
odoo/addons/shopinvader_product_seo/__manifest__.py
odoo/addons/shopinvader_product_seo/i18n/shopinvader_product_seo.pot
odoo/addons/shopinvader_product_seo/models/__init__.py
odoo/addons/shopinvader_product_seo/models/product_category.py
odoo/addons/shopinvader_product_seo/models/product_template.py
odoo/addons/shopinvader_product_seo/models/seo_title_mixin.py
odoo/addons/shopinvader_product_seo/readme/CONTRIBUTORS.rst
odoo/addons/shopinvader_product_seo/readme/DESCRIPTION.rst
odoo/addons/shopinvader_product_seo/schemas/__init__.py
odoo/addons/shopinvader_product_seo/schemas/category.py
odoo/addons/shopinvader_product_seo/schemas/product.py
odoo/addons/shopinvader_product_seo/static/description/index.html
odoo/addons/shopinvader_product_seo/views/product_category.xml
odoo/addons/shopinvader_product_seo/views/product_template.xml
odoo_addon_shopinvader_product_seo-16.0.1.0.0.3.dist-info/METADATA
odoo_addon_shopinvader_product_seo-16.0.1.0.0.3.dist-info/WHEEL
odoo_addon_shopinvader_product_seo-16.0.1.0.0.3.dist-info/top_level.txt
odoo_addon_shopinvader_product_seo-16.0.1.0.0.3.dist-info/RECORD
